compass/experiments/__init__.py
compass/experiments/hierarchy.py
compass/experiments/interface.py
compass/experiments/people.py
compass/experiments/reports_interface.py
compass_interface_experiments-0.27.0.dist-info/LICENSE
compass_interface_experiments-0.27.0.dist-info/WHEEL
compass_interface_experiments-0.27.0.dist-info/METADATA
compass_interface_experiments-0.27.0.dist-info/RECORD
